{
  "metadata": {
    "scraped_at": "2026-06-02T05:18:56.498143+00:00",
    "subject": "SILP",
    "subject_title": "School Improvement and Leaders",
    "total_courses": 5,
    "scraper_version": "memory-safe-v2.0"
  },
  "courses": [
    {
      "subject": "SILP",
      "course_code": "6001",
      "title": "Issues and Advances in School Improvement",
      "credits": "3.00",
      "terms": [
        {
          "term_code": "2380",
          "term_name": "2025-26 Term 1",
          "schedule": [
            {
              "section": "--LEC (1737)",
              "meetings": [
                {
                  "time": "Mo 6:30PM - 9:00PM",
                  "location": "Wong Foo Yuan Bldg UG02",
                  "instructor": "Dr. CHU Kai Wing, \nProfessor CHEUNG Chi Keung Alan",
                  "dates": "1/9, 8/9, 15/9, 22/9, 29/9"
                },
                {
                  "time": "Mo 6:30PM - 9:00PM",
                  "location": "Wong Foo Yuan Bldg UG02",
                  "instructor": "Dr. CHU Kai Wing, \nProfessor CHEUNG Chi Keung Alan",
                  "dates": "13/10, 20/10, 27/10, 3/11, 10/11, 17/11, 24/11, 1/12"
                }
              ],
              "availability": {
                "capacity": "999",
                "enrolled": "40",
                "waitlist_capacity": "0",
                "waitlist_total": "0",
                "available_seats": "959",
                "status": "Open"
              },
              "class_attributes": "Cantonese and English"
            }
          ]
        }
      ],
      "description": "This module will critically examine key current issues related to school improvement. These issues include postmodern views on leadership, management and school change, creating schools as learning as well as knowledge creation and management organizations, improvement plans, whole-school curriculum planning, inclusiveness, student and parental involvement in improvement and partnership development. Up-to-date theories and practice drawing on school improvement experience from international and comparative perspectives will also be covered, as well as critical analysis of self-managing schools and school effectiveness and improvement research. The perspectives of stakeholders such as teachers, principals, policy-makers, students and parents on school improvement will also be discussed.",
      "enrollment_requirement": "For students in MA School Improvement and Leadership",
      "course_attributes": "",
      "academic_career": "Postgraduate - Taught",
      "grading_basis": "Graded",
      "component": "Lecture",
      "campus": "Main Campus",
      "academic_group": "Div of Education",
      "academic_org": "Div of Education",
      "learning_outcomes": "To enable participant to\n1. acquire understanding of different perspectives and theories related to school improvement;\n2. apply the acquired knowledge to analyze how schools develop and improve;\n3. acquire practical strategies to initiate school improvement;\n4. critically examine different school improvement cases.\n\n(Individual course teachers may update the learning outcome as and whenever necessary.)",
      "course_syllabus": "(Please refer to the course outline of respective teacher for details.)",
      "assessment_types": {},
      "feedback_evaluation": "Feedback from students will be collected through email exchanges and course-end evaluation.\n\n(For reference only, please refer to the course outline of respective teacher for details.)",
      "required_readings": "(Required readings (if any) would depend on individual course teachers. Please refer to the course outline of respective teacher for details.)",
      "recommended_readings": "(Recommended readings (if any) would depend on individual course teachers. Please refer to the course outline of respective teacher for details.)"
    },
    {
      "subject": "SILP",
      "course_code": "6002",
      "title": "Leadership for Student Learning",
      "credits": "3.00",
      "terms": [
        {
          "term_code": "2390",
          "term_name": "2025-26 Term 2",
          "schedule": [
            {
              "section": "--LEC (4612)",
              "meetings": [
                {
                  "time": "We 6:30PM - 9:00PM",
                  "location": "Lee Shau Kee Archi Bldg G04",
                  "instructor": "Professor QIAN Haiyan",
                  "dates": "7/1, 14/1, 21/1, 28/1, 4/2, 11/2"
                },
                {
                  "time": "We 6:30PM - 9:00PM",
                  "location": "Lee Shau Kee Archi Bldg G04",
                  "instructor": "Professor QIAN Haiyan",
                  "dates": "25/2, 4/3, 11/3, 18/3, 25/3, 1/4, 8/4"
                }
              ],
              "availability": {
                "capacity": "999",
                "enrolled": "40",
                "waitlist_capacity": "0",
                "waitlist_total": "0",
                "available_seats": "959",
                "status": "Open"
              },
              "class_attributes": "English only"
            }
          ]
        }
      ],
      "description": "The heart of school leadership and professional development is the improvement of student life and learning. This module will critically examine key leadership and professional development issues specifically as they relate to learning, teaching and curriculum in the school context. With reference to different levels of school leadership, the course is designed to promote the critical evaluation of theories related to effective learning and teaching and their application to local classrooms and schools. Course content includes current local and international thinking in areas such as school restructuring, instructional and curriculum leadership, teacher professional development, action research and reflective practice, teacher motivation, team building, peer observation and developmental supervision. Students are encouraged to pool theoretical and craft knowledge to develop approaches and strategies to lead and manage effective learning in their own schools.",
      "enrollment_requirement": "For students in MA School Improvement and Leadership",
      "course_attributes": "",
      "academic_career": "Postgraduate - Taught",
      "grading_basis": "Graded",
      "component": "Lecture",
      "campus": "Main Campus",
      "academic_group": "Div of Education",
      "academic_org": "Div of Education",
      "learning_outcomes": "To enable participant to\n\n1. Developed a stance of what effective leadership means in Hong Kong.\n\n2. A firm understanding of the latest school leadership literature.\n\n3. Understood the factors contributing to effective leadership in Hong Kong schools.\n\n4. Appreciated the applicability of the theories in Hong Kong context\n\n5. Proposed a number of key approaches and strategies to lead and manage effective learning in your school.\n\n6. Reflected upon leadership.\n\n7. Enjoyed your learning and the community you share with other learners.\n\n(Individual course teachers may update the learning outcome as and whenever necessary.)",
      "course_syllabus": "1. Foundations of management and leadership theories\n\n2. Accountability and governance in schools\n\n3. Leadership and school improvement\n\n4. Leadership and teacher development\n\n5. Leadership and student learning\n\n6. Integration\n\n(For reference only, please refer to the course outline of respective teacher for details.)",
      "assessment_types": {
        "Essays": "50",
        "Project": "50"
      },
      "feedback_evaluation": "Class discussion\n\nPeer evaluations and feedback\n\n(For reference only, please refer to the course outline of respective teacher for details.)",
      "required_readings": "(Required readings (if any) would depend on individual course teachers. Please refer to the course outline of respective teacher for details.)",
      "recommended_readings": "(Recommended readings (if any) would depend on individual course teachers. Please refer to the course outline of respective teacher for details.)"
    },
    {
      "subject": "SILP",
      "course_code": "6003",
      "title": "Evaluation for School Improvement",
      "credits": "1.50",
      "terms": [
        {
          "term_code": "2390",
          "term_name": "2025-26 Term 2",
          "schedule": [
            {
              "section": "--LEC (3521)",
              "meetings": [
                {
                  "time": "Mo 6:30PM - 9:00PM",
                  "location": "Sino Building 614",
                  "instructor": "Professor OU Dongshu",
                  "dates": "5/1, 12/1, 19/1, 26/1, 2/2, 9/2"
                },
                {
                  "time": "Mo 6:30PM - 9:00PM",
                  "location": "Sino Building 614",
                  "instructor": "Professor OU Dongshu",
                  "dates": "23/2"
                }
              ],
              "availability": {
                "capacity": "999",
                "enrolled": "38",
                "waitlist_capacity": "0",
                "waitlist_total": "0",
                "available_seats": "961",
                "status": "Open"
              },
              "class_attributes": "Cantonese and English"
            }
          ]
        }
      ],
      "description": "This module focuses on different perspectives, models and methodologies for evaluating school improvement. First, various evaluation ideologies and perspectives will be examined. Secondly, different models of formative and summative methods of evaluation, role of stakeholders in school-based evaluation and their relationships with school improvement would be explored. A workshop on the use of SPSS for basic statistical skills and a follow-up tutorial on data entry and analyses will be given to each student. Finally, issues on school based evaluation, external review and teacher evaluation would be discussed.",
      "enrollment_requirement": "For students in MA School Improvement and Leadership",
      "course_attributes": "",
      "academic_career": "Postgraduate - Taught",
      "grading_basis": "Graded",
      "component": "Lecture",
      "campus": "Main Campus",
      "academic_group": "Div of Education",
      "academic_org": "Div of Education",
      "learning_outcomes": "After the course, students will be able:\n1. To become familiar with the body of knowledge that comprises current approaches to educational evaluation and a number of current issues related to school improvement.\n2. To define the problems and questions in educational evaluation and to decide what to measure in assessing school performance.\n3. To understand the requirements in establishing a quality assurance mechanism within the school and the strategies to build up such a mechanism.\n4. To acquire the skills and techniques in school self-evaluation and to formulate the necessary tools and instruments that aligns with the realization of the school’s goals and missions.\n5. To understand the functions and roles of both the external school reviews and school self-evaluation in relation to school improvement, including its strengths and weaknesses.\n\n(Individual course teachers may update the learning outcome as and whenever necessary.)",
      "course_syllabus": "1. Educational Evaluation and Research from International Perspective\n2. Educational Evaluation and Improvement in Local Context\n3. Assessing Students’ Cognitive Domains\n4. Assessing Students’ Affective and Social Domains\n5. Workshop: Hands on Experience on Statistical Skills and Techniques\n6. Educational Evaluation: Development vs Accountability\n7. Tutorial SPSS, Data Entry and Analysis\n\n(For reference only, please refer to the course outline of respective teacher for details.)",
      "assessment_types": {},
      "feedback_evaluation": "Feedback from students to be collected via course-end evaluation, class meetings, and Email exchanges.\n\n(For reference only, please refer to the course outline of respective teacher for details.)",
      "required_readings": "(Required readings (if any) would depend on individual course teachers. Please refer to the course outline of respective teacher for details.)",
      "recommended_readings": "(Recommended readings (if any) would depend on individual course teachers. Please refer to the course outline of respective teacher for details.)"
    },
    {
      "subject": "SILP",
      "course_code": "6004",
      "title": "Field Experience",
      "credits": "1.50",
      "terms": [
        {
          "term_code": "2380",
          "term_name": "2025-26 Term 1",
          "schedule": [
            {
              "section": "--LEC (4577)",
              "meetings": [
                {
                  "time": "Fr 6:30PM - 9:00PM",
                  "location": "Esther Lee Bldg 202",
                  "instructor": "Dr. CHU Kai Wing",
                  "dates": "5/9, 12/9, 19/9"
                },
                {
                  "time": "Fr 6:30PM - 9:00PM",
                  "location": "Esther Lee Bldg 202",
                  "instructor": "Dr. CHU Kai Wing",
                  "dates": "24/10"
                }
              ],
              "availability": {
                "capacity": "999",
                "enrolled": "37",
                "waitlist_capacity": "0",
                "waitlist_total": "0",
                "available_seats": "962",
                "status": "Open"
              },
              "class_attributes": "Cantonese only"
            }
          ]
        }
      ],
      "description": "In this module, students will participate in/ visit schools and other educational settings that are involved in exemplary schools, successful educational improvement projects, curriculum development efforts, and professional development activities. They will participate in seminars and workshops to learn strategies of school improvement. Through field study and various modes of learning, students will to be able to bridge theory and practice in school improvement for their own needs.",
      "enrollment_requirement": "For students in MA School Improvement and Leadership",
      "course_attributes": "",
      "academic_career": "Postgraduate - Taught",
      "grading_basis": "Graded",
      "component": "Lecture",
      "campus": "Main Campus",
      "academic_group": "Div of Education",
      "academic_org": "Div of Education",
      "learning_outcomes": "Through class participation, field experience and other learning activities of different course components, students should be able to:\n1. understand the core ideas, logic, relevance and implications of educational change\n2. grasp the key concepts and their interrelationship and theoretical frameworks of educational change, school improvement and leadership\n3. appreciate the contexts, rationales and justification of specific cases of school improvement\n4. reflect on their day-to-day practices for educational change and school improvement and share their personal experience, views and critical comments\n5. apply what they have learnt from the course to writing a proposal with literature/research basis, rationales and justification in context on the implementation and evaluation of a school improvement project\n\n(Individual course teachers may update the learning outcome as and whenever necessary.)",
      "course_syllabus": "(Please refer to the course outline of respective teacher for details.)",
      "assessment_types": {},
      "feedback_evaluation": "Feedback from students to be collected via course-end evaluation, class meetings, and Email exchanges.\n\n(For reference only, please refer to the course outline of respective teacher for details.)",
      "required_readings": "(Required readings (if any) would depend on individual course teachers. Please refer to the course outline of respective teacher for details.)",
      "recommended_readings": "(Recommended readings (if any) would depend on individual course teachers. Please refer to the course outline of respective teacher for details.)"
    },
    {
      "subject": "SILP",
      "course_code": "6005",
      "title": "Guided Improvement Project",
      "credits": "6.00",
      "terms": [
        {
          "term_code": "2380",
          "term_name": "2025-26 Term 1",
          "schedule": [
            {
              "section": "AJ01-PRJ (1327)",
              "meetings": [
                {
                  "time": "TBA",
                  "location": "No Room Required",
                  "instructor": "Professor CHEUNG Chi Keung Alan",
                  "dates": "01/09/2025 - 24/11/2025"
                }
              ],
              "availability": {
                "capacity": "999",
                "enrolled": "0",
                "waitlist_capacity": "0",
                "waitlist_total": "0",
                "available_seats": "999",
                "status": "Open"
              },
              "class_attributes": "Cantonese and English"
            }
          ]
        },
        {
          "term_code": "2390",
          "term_name": "2025-26 Term 2",
          "schedule": [
            {
              "section": "BJ01-PRJ (1332)",
              "meetings": [
                {
                  "time": "TBA",
                  "location": "No Room Required",
                  "instructor": "Dr. CHU Kai Wing, \nDr. HO Sai Mun Stanley, \nDr. LAU Ngar Sze, \nProfessor CHEUNG Chi Keung Alan, \nProfessor LEE Daphnee Hui Lin, \nProfessor QIAN Haiyan, \nProfessor ZOU Xiaoping",
                  "dates": "05/01/2026 - 13/04/2026"
                }
              ],
              "availability": {
                "capacity": "999",
                "enrolled": "38",
                "waitlist_capacity": "0",
                "waitlist_total": "0",
                "available_seats": "961",
                "status": "Open"
              },
              "class_attributes": "Cantonese and English"
            }
          ]
        }
      ],
      "description": "Participants will participate in an improvement project under the guidance and support of practicum supervisors. They may conduct the research in their workplace, if appropriate. The focus of improvement may be related to organizational, curriculum, teaching and learning aspects in a school or other educational organizations. The project should include an identification of a problem, a plan for initiating change based on theory and/ or other school practices, implementation of the plan, and evaluation of the change outcomes. Participants will be placed in small support groups who are expected to share experiences and exchange ideas gained from the project.",
      "enrollment_requirement": "For students in MA School Improvement and Leadership",
      "course_attributes": "",
      "academic_career": "Postgraduate - Taught",
      "grading_basis": "Graded",
      "component": "Lecture\nProject",
      "campus": "Main Campus",
      "academic_group": "Div of Education",
      "academic_org": "Div of Education",
      "learning_outcomes": "After the guided improvement projects, students will be able:\n1. To become familiar with the body of knowledge that comprises current approaches to educational research in school leadership and improvement.\n2. To define the problems and questions in the organizations or schools that they are working for and to set priority in the agenda of improvement.\n3. To solve the problems or address the questions through a systematic process of collecting and analyzing empirical information/ data.\n4. To apply the skills and techniques in quantitative or qualitative research methodologies in answering the research questions.\n5. To get significant meanings from the research findings and to present the findings properly with appropriate means.\n6. To formulate suggestions and recommendations of school improvement based on the empirical findings from the study, that aligns with the realization of the school’s goals and missions.\n7. To understand the functions and roles of an scientific project in relation to school improvement, including its strengths and weaknesses.\n\n(Individual course teachers may update the learning outcome as and whenever necessary.)",
      "course_syllabus": "(Please refer to the course outline of respective teacher for details.)",
      "assessment_types": {},
      "feedback_evaluation": "(Please refer to the course outline of respective teacher for details.)",
      "required_readings": "(Required readings (if any) would depend on individual course teachers. Please refer to the course outline of respective teacher for details.)",
      "recommended_readings": "(Recommended readings (if any) would depend on individual course teachers. Please refer to the course outline of respective teacher for details.)"
    }
  ]
}
